vivid/node/__init__.py
vivid_node-0.5.583.dist-info/LICENSE
vivid_node-0.5.583.dist-info/METADATA
vivid_node-0.5.583.dist-info/WHEEL
vivid_node-0.5.583.dist-info/top_level.txt
vivid_node-0.5.583.dist-info/zip-safe
vivid_node-0.5.583.dist-info/RECORD
